rock_ptarmigan/__init__.py
rock_ptarmigan/main.py
rock_ptarmigan-1.0.3.dist-info/licenses/LICENSE.txt
rock_ptarmigan-1.0.3.dist-info/METADATA
rock_ptarmigan-1.0.3.dist-info/WHEEL
rock_ptarmigan-1.0.3.dist-info/entry_points.txt
rock_ptarmigan-1.0.3.dist-info/top_level.txt
rock_ptarmigan-1.0.3.dist-info/RECORD
