Metadata-Version: 2.4
Name: rock_ptarmigan
Version: 1.0.3
Summary: Approximate value evaluation.
Author-email: Takayuki Kamiyama <karuma.reason@gmail.com>
License: The MIT License
Classifier: Programming Language :: Python :: 3.13
License-File: LICENSE.txt
Requires-Dist: opencv-python
Requires-Dist: python-dotenv
Requires-Dist: scikit-learn
Requires-Dist: tensorflow
Requires-Dist: opencv-python
Dynamic: license-file
